Workbook

Sheet HYPNOBOX
A1: ÁREA: | B1: COMERCIAL
A2: PATROCINADOR | B2: MICHEL
A3: NA-TI | B3: DANIEL
A4: DATA | B4: 46055
A5: CITY | G5: porque a sua nota foi esta?
A7: ÁREA | B7: PROCESSO | C7: REQUISITO | D7: Descrição | E7: PESO | F7: DESCRIÇÃO PESO | G7: POSITIVO | H7: NEGATIVO | I7: NOTA
A8: GERAL | B8: EMPREENDIMENTO | C8: CADASTRO | D8: Realizar o cadastro dos dados relacionados ao empreendimento, como data de lançamento, número da RI, data de entrega, área, nome fantasia e razão social da empresa, endereço, posição geográfica, conta de pagamento, código do empreendimento no erp, amenidades, pontos fortes e afins. | E8: 5 | F8: =VLOOKUP(E8,REGRAS!$A$2:$B$6,2,FALSE) -> Eliminatório (Must-have) | G8: conseguimos cadastrar todas as informações necessários para os demais processos | H8: precisa ser feito pela hypnobox para garantir funcionamento | I8: 4
A9: GERAL | B9: EMPREENDIMENTO | C9: MATERIAL DE APOIO A VENDA | D9: Permite anexar ao empreendimento material que auxilie o processo de venda, como vídeos, imagens e scripts de venda, quebra de resistencia e afins. | E9: 1 | F9: =VLOOKUP(E9,REGRAS!$A$2:$B$6,2,FALSE) -> Baixo valor na compra (Nice-to-have) | H9: não possui capacidade de armazenar e fornecer material de suporte a venda | I9: 2
A10: GERAL | B10: EMPREENDIMENTO | C10: UHs/LOTE | D10: Cadastro das unidades/lotes com suas características (m2, andar, local e etc) | E10: 5 | F10: =VLOOKUP(E10,REGRAS!$A$2:$B$6,2,FALSE) -> Eliminatório (Must-have) | G10: Atende corretamente | I10: 5
A11: GERAL | B11: EMPREENDIMENTO | C11: UHs/LOTE>TAGS | D11: Opção de marcar unidades, como, promoção, decorada, cobertura ou outra tag desejada | E11: 2 | F11: =VLOOKUP(E11,REGRAS!$A$2:$B$6,2,FALSE) -> Desejável | G11: Possuí algo neste sentido mas não conseguimos utilizar | I11: 3
A12: GERAL | B12: EMPREENDIMENTO | C12: UHs/LOTE>AGLUTINADOR | D12: Permite unificar unidades avulsas em uma única unidade para a venda, incluso valor próprio | E12: 3 | F12: =VLOOKUP(E12,REGRAS!$A$2:$B$6,2,FALSE) -> Importante | H12: não é possível criar agregadores de unidades | I12: 0
A13: GERAL | B13: EMPREENDIMENTO | C13: UHs/LOTE>COMBO | D13: Permite aglutinar unidades apenas como sugestão de venda com valor próprio (desconto por volume) | E13: 3 | F13: =VLOOKUP(E13,REGRAS!$A$2:$B$6,2,FALSE) -> Importante | H13: não é possível criar agregadores de unidades | I13: 0
A14: GERAL | B14: EMPREENDIMENTO | C14: TABELA DE PREÇO>CADASTRO | D14: Cadastrar tabelas de preço para as unidades | E14: 5 | F14: =VLOOKUP(E14,REGRAS!$A$2:$B$6,2,FALSE) -> Eliminatório (Must-have) | G14: é possível realizar o cadastramento de quase todas os planos de venda/valores | H14: ainda não conseguiram garantir o funcionamento de financiamento próprio com 2 indices (incc + ipca) | I14: 4
A15: GERAL | B15: EMPREENDIMENTO | C15: TABELA DE PREÇO>ATUALIZAÇÃO MONETÁRIA | D15: Permite informar atualização monetária para atualização das tabelas de preço, inclusive, com regra de arredondamento e calendário de execução. | E15: 5 | F15: =VLOOKUP(E15,REGRAS!$A$2:$B$6,2,FALSE) -> Eliminatório (Must-have) | G15: Tem a possibilidade de aplicar um indice | H15: Não é possível realziar via API e é burocrática no sistema | I15: 3
A16: GERAL | B16: EMPREENDIMENTO | C16: TABELA DE PREÇO>EVOLUÇÃO DO PREÇO | D16: Permite verificar, para uma unidade, a evolução de preço ao longo do tempo | E16: 2 | F16: =VLOOKUP(E16,REGRAS!$A$2:$B$6,2,FALSE) -> Desejável | H16: Não possuí esta funcionalidade | I16: 0
A17: GERAL | B17: EMPREENDIMENTO | C17: TABELA DE PREÇO>EXCEÇÕES > AGLUTINADOR | D17: Permite cadastrar preço para unidades aglutinadas. | E17: 3 | F17: =VLOOKUP(E17,REGRAS!$A$2:$B$6,2,FALSE) -> Importante | H17: Não possuí esta funcionalidade | I17: 0
A18: GERAL | B18: EMPREENDIMENTO | C18: TABELA DE PREÇO>EXCEÇÕES > COMBO | D18: Permite cadastrar preço para unidades agrupadas no combo. | E18: 3 | F18: =VLOOKUP(E18,REGRAS!$A$2:$B$6,2,FALSE) -> Importante | H18: Não possuí esta funcionalidade | I18: 0
A19: GERAL | B19: EMPREENDIMENTO | C19: API INTEGRAÇÃO | D19: Integração das rotinas do empreendimento (cadastro, material de apoio a vendas, uhs, tabela de preço) via API | E19: 4 | F19: =VLOOKUP(E19,REGRAS!$A$2:$B$6,2,FALSE) -> Crítico para operação/adaptação | H19: não achamos um endpoint real para nenhuma das opções do Empreendimento | I19: 1
A20: GERAL | B20: STATUS UNIDADE | C20: CADASTRO | D20: Permite criar status além do padrão do sistema, permitindo controle de situações fora do esperado, como, por exemplo, suspensa aguardando decoração. | E20: 2 | F20: =VLOOKUP(E20,REGRAS!$A$2:$B$6,2,FALSE) -> Desejável | G20: Permite criar status avulso | I20: 5
A21: GERAL | B21: STATUS UNIDADE | C21: ESPELHO DE VENDA | D21: Deve permitir consulta aos status da unidade. | E21: 5 | F21: =VLOOKUP(E21,REGRAS!$A$2:$B$6,2,FALSE) -> Eliminatório (Must-have) | G21: Permite visualização do espelho formatado por andar | I21: 5
A22: GERAL | B22: STATUS UNIDADE | C22: ESPELHO DE VENDA>API | D22: Permite consultar o status das unidades através de API | E22: 4 | F22: =VLOOKUP(E22,REGRAS!$A$2:$B$6,2,FALSE) -> Crítico para operação/adaptação | G22: Permite através de adaptação, com alta complexidade no objeto de retorno | I22: 4
A23: GERAL | B23: STATUS UNIDADE | C23: ESPELHO DE VENDA>ACESSO EXTERNO | D23: Permite acesso externo, não logado, ao espelho de vendas | E23: 3 | F23: =VLOOKUP(E23,REGRAS!$A$2:$B$6,2,FALSE) -> Importante | G23: Permite através de link | I23: 5
A24: GERAL | B24: ACESSO | C24: USUÁRIOS | D24: Cadastro de usuários do sistema | E24: 5 | F24: =VLOOKUP(E24,REGRAS!$A$2:$B$6,2,FALSE) -> Eliminatório (Must-have) | G24: Possui cadastro de usuários | I24: 5
A25: GERAL | B25: ACESSO | C25: USUÁRIOS>INTEGRAÇÃO AD | D25: Permite integrar com o AD com filtro apenas para usuários pertencentes ao grupo "Nome do Sistema" | E25: 3 | F25: =VLOOKUP(E25,REGRAS!$A$2:$B$6,2,FALSE) -> Importante | H25: Não possuí integração com o AD | I25: 0
A26: GERAL | B26: ACESSO | C26: CARGOS/GRUPOS | D26: Permite agrupar usuários e suas permissões (Corretor, Gerente, Diretor) | E26: 4 | F26: =VLOOKUP(E26,REGRAS!$A$2:$B$6,2,FALSE) -> Crítico para operação/adaptação | G26: Possuí cargos e pemissionamento ligado ao cargo | I26: 5
A27: GERAL | B27: ACESSO | C27: EMPREENDIMENTOS | D27: Permite agrupar usuários a empreendimentos em grupos distintos | E27: 3 | F27: =VLOOKUP(E27,REGRAS!$A$2:$B$6,2,FALSE) -> Importante | G27: Possuí vinculo do usuário com o empreendimento | I27: 5
A28: GERAL | B28: ACESSO | C28: EXTERNOS>IMOBILIÁRIA | D28: Cadastrar as imobiliárias e as informações para contato (comercial, administrativo, financeiro) | E28: 3 | F28: =VLOOKUP(E28,REGRAS!$A$2:$B$6,2,FALSE) -> Importante | H28: Não possui cadastro de imobiliárias | I28: 0
A29: GERAL | B29: ACESSO | C29: EXTERNOS>IMOBILIÁRIA>GESTOR | D29: Permite vincular Usuários a Imobiliárias | E29: 3 | F29: =VLOOKUP(E29,REGRAS!$A$2:$B$6,2,FALSE) -> Importante | H29: Não possui cadastro de imobiliárias | I29: 0
A30: GERAL | B30: ACESSO | C30: EXTERNOS>IMOBILIÁRIA>VINCULO CORRETOR | D30: Rotina para veinculação de corretores a imobiliária (utilizando o contato/gestor para aprovação da soliticação de agregação feita pelo corretor | E30: 3 | F30: =VLOOKUP(E30,REGRAS!$A$2:$B$6,2,FALSE) -> Importante | H30: Não possui cadastro de imobiliárias | I30: 0
A31: GERAL | B31: ACESSO | C31: EXTERNOS>CORRETORES | D31: Autocadastro dos corretores e solicitação de ingresso em uma imobiliária | E31: 3 | F31: =VLOOKUP(E31,REGRAS!$A$2:$B$6,2,FALSE) -> Importante | H31: Não possui cadastro de corretores externos | I31: 0
A32: GERAL | B32: ACESSO | C32: EXTERNOS>API INTEGRAÇÃO | D32: Permite realizar ações junto a imobiliárias e corretores através de API | E32: 3 | F32: =VLOOKUP(E32,REGRAS!$A$2:$B$6,2,FALSE) -> Importante | H32: não existe correlação de gestores e imobiliárias | I32: 0
A33: RESERVA | B33: GERAL | C33: CADASTRO>REQUISIÇÃO | D33: Permite requisitar uma reserva avulsa para uma determinada unidade, armazenando dados de log | E33: 5 | F33: =VLOOKUP(E33,REGRAS!$A$2:$B$6,2,FALSE) -> Eliminatório (Must-have) | G33: Permite realizar troca de status de maneira avulsa | H33: Não há controle de tempo quando utilizada esta função | I33: 3
A34: RESERVA | B34: GERAL | C34: TROCA DE RESPONSÁVEL | D34: Permite, ao trocar ou suspender o responsável pela imobiliária vinculada, que as reservas vinculadas sejam redirecionadas para o novo gestor | E34: 2 | F34: =VLOOKUP(E34,REGRAS!$A$2:$B$6,2,FALSE) -> Desejável | H34: Não há controle de responsáveis pela reserva já que não há requisição de reserva | I34: 0
A35: RESERVA | B35: GERAL | C35: FILA | D35: Permite enfileirar as requisições de reserva por ordem de chegada, guardando informações de requisitante, data, imobiliária e responsável | E35: 5 | F35: =VLOOKUP(E35,REGRAS!$A$2:$B$6,2,FALSE) -> Eliminatório (Must-have) | H35: Não há controle de fila de reserva | I35: 0
A36: RESERVA | B36: GERAL | C36: TEMPO DE VIDA>VENCIMENTO | D36: Requisições de reserva aprovadas e ativas precisam de controle de tempo de vida e serem canceladas quando vencidas | E36: 4 | F36: =VLOOKUP(E36,REGRAS!$A$2:$B$6,2,FALSE) -> Crítico para operação/adaptação | G36: Há controle simples de tempo de vida, com parametro único, começando a contar no momento do cadastro, já que não há requisição ou fila | H36: O tempo continua correndo mesmo com uma proposta em análise, vencendo outra pessoa pode reservar mesmo com a outra proposta ativa. | I36: 2
A37: RESERVA | B37: GERAL | C37: TEMPO DE VIDA>EXTENSÃO | D37: Requisições de reserva aprovadas e ativas podem ter seu tempo de vencimento extendido | E37: 4 | F37: =VLOOKUP(E37,REGRAS!$A$2:$B$6,2,FALSE) -> Crítico para operação/adaptação | H37: não é possível extender o prazo de uma reserva. | I37: 0
A38: RESERVA | B38: GERAL | C38: APROVAÇÃO | D38: Requisições de reserva precisam ser aprovadas, mesmo que seja apenas quando forem a reserva "da vez" (fila) | E38: 4 | F38: =VLOOKUP(E38,REGRAS!$A$2:$B$6,2,FALSE) -> Crítico para operação/adaptação | H38: Não existe aprovação de reservas | I38: 0
A39: RESERVA | B39: GERAL | C39: APROVAÇÃO>MULTI-NÍVEL | D39: Possível, para certas filas, exigir mais de uma aprovação para aceitar uma reserva | E39: 2 | F39: =VLOOKUP(E39,REGRAS!$A$2:$B$6,2,FALSE) -> Desejável | H39: Não existe aprovação de reservas | I39: 0
A40: RESERVA | B40: GERAL | C40: API INTEGRAÇÃO | D40: Permitir a consulta, adição e aprovação de reservas por API | E40: 4 | F40: =VLOOKUP(E40,REGRAS!$A$2:$B$6,2,FALSE) -> Crítico para operação/adaptação | H40: Não existe integração. | I40: 0
A41: RESERVA | B41: DESAFIANTE | C41: CADASTRO | D41: Permite que a reserva atualmente em vigor seja desafiada, e, se o desafio for aprovado, o tempo para vencimento é reduzido e, caso expirado, a desafiante passa automaticamente para a primeira posição da fila. | E41: 2 | F41: =VLOOKUP(E41,REGRAS!$A$2:$B$6,2,FALSE) -> Desejável | H41: Não há controle de desafiante | I41: 0
A42: RESERVA | B42: NOTIFICAÇÕES | C42: MEIOS (EMAIL, SMS, WHATSAPP) | D42: Informa por meios eletônicos (email, sms, whatsapp) os todos os eventos da reserva | E42: 4 | F42: =VLOOKUP(E42,REGRAS!$A$2:$B$6,2,FALSE) -> Crítico para operação/adaptação | G42: Só existe aviso de reserva por email | H42: Não há aviso de proximidade da expiração ou da expiração da reserva, nem outros meios de comunicação. | I42: 2
A43: RESERVA | B43: NOTIFICAÇÕES | C43: LINK PORTAL | D43: Permite, nas mensagens, ao menos clicar e já entrar na págia de ação para aquele evento da reserva | E43: 2 | F43: =VLOOKUP(E43,REGRAS!$A$2:$B$6,2,FALSE) -> Desejável | H43: Esta funcionalidade não existe | I43: 0
A44: RESERVA | B44: SINAL | C44: GERAÇÃO COM VINCULO NA RESERVA | D44: Permite vincular um pagamento mínimo para confirmação automática da reserva, não necessitando aprovação, quando permitido ao requisitante e informado mínimo na tabela de preço da unidade. | E44: 1 | F44: =VLOOKUP(E44,REGRAS!$A$2:$B$6,2,FALSE) -> Baixo valor na compra (Nice-to-have) | H44: Esta funcionalidade não existe | I44: 0
A45: RESERVA | B45: SINAL | C45: RECEBIMENTO>CARTÃO | D45: Recebimento com cartão da reserva | E45: 1 | F45: =VLOOKUP(E45,REGRAS!$A$2:$B$6,2,FALSE) -> Baixo valor na compra (Nice-to-have) | H45: Esta funcionalidade não existe | I45: 0
A46: RESERVA | B46: SINAL | C46: RECEBIMENTO>PIX | D46: Recebimento com pix da reserva | E46: 1 | F46: =VLOOKUP(E46,REGRAS!$A$2:$B$6,2,FALSE) -> Baixo valor na compra (Nice-to-have) | H46: Esta funcionalidade não existe | I46: 0
A47: RESERVA | B47: SINAL | C47: DEVOLUÇÃO/CANCELAMENTO | D47: Caso a reserva caia pelo tempo e houver pagamento vinculado o mesmo é devolvido ao pagante de forma automatizada (Pix) | E47: 1 | F47: =VLOOKUP(E47,REGRAS!$A$2:$B$6,2,FALSE) -> Baixo valor na compra (Nice-to-have) | H47: Esta funcionalidade não existe | I47: 0
A48: PV | B48: CALCULO | C48: PARCELA COM CORREÇÃO MONETÁRIA | D48: Realiza o calculo do valor presente quando a parcela possui correção monetária | E48: 4 | F48: =VLOOKUP(E48,REGRAS!$A$2:$B$6,2,FALSE) -> Crítico para operação/adaptação | H48: Não leva em consideração a correção | I48: 0
A49: PV | B49: CALCULO | C49: PARCELA SEM CORREÇÃO MONETÁRIA | D49: Realiza o calculo do valor presente quando a parcela não possui correção monetária | E49: 5 | F49: =VLOOKUP(E49,REGRAS!$A$2:$B$6,2,FALSE) -> Eliminatório (Must-have) | G49: Calcula corretamente | H49: Se informar data anterior ao mês atual o PV fica positivo | I49: 4
A50: PV | B50: CALCULO | C50: FLUXO PRÉ-DEFINIDO | D50: Permite cadastrar fluxos pré-definidos vinculados aos tipos de parcela (Imóvel, Veículo, Bens de alto valor) com fluxo de pagamento e data de início (venda, parela, chaves, final) | E50: 3 | F50: =VLOOKUP(E50,REGRAS!$A$2:$B$6,2,FALSE) -> Importante | H50: Esta funcionalidade não existe | I50: 0
A51: PV | B51: CADASTRO | C51: FLUXO PRÉ-DEFINIDO>VALOR REAL DIFERENTE | D51: Ao calcular, ando há fluxo pré-definido, permite informar o valor real do bem, descontando do fluxo o valor original negociado, porém, calculando o PV com o valor real. | E51: 3 | F51: =VLOOKUP(E51,REGRAS!$A$2:$B$6,2,FALSE) -> Importante | H51: Esta funcionalidade não existe | I51: 0
A52: PV | B52: CADASTRO | C52: FLUXO PRÉ-DEFINIDO>QUANTIDADE DE PARCELAS | D52: Dermite informar quantidade de parcelas para quantidade de das fluxos prés definido quantidade, inclusive, com regra pré arredondamento c calendário pré execução. | E52: 3 | F52: =VLOOKUP(E52,REGRAS!$A$2:$B$6,2,FALSE) -> Importante | H52: Esta funcionalidade não existe | I52: 0
A53: SIMULAÇÃO | B53: RESERVA | C53: FLUXO DA RESERVA | D53: Permite seguir o fluxo da reserva quando na simulação | E53: 5 | F53: =VLOOKUP(E53,REGRAS!$A$2:$B$6,2,FALSE) -> Eliminatório (Must-have) | G53: Permite | H53: Não há onde observar todas as reservas | I53: 3
A54: SIMULAÇÃO | B54: CENÁRIOS | C54: MULTI-VERSÃO | D54: Permite gravar múltiplas versões da negociação com o cliente | E54: 3 | F54: =VLOOKUP(E54,REGRAS!$A$2:$B$6,2,FALSE) -> Importante | H54: Esta funcionalidade não existe | I54: 0
A55: SIMULAÇÃO | B55: PV | C55: FLUXO DO PV | D55: Permite seguir o fluxo do pv quando na simulação | E55: 5 | F55: =VLOOKUP(E55,REGRAS!$A$2:$B$6,2,FALSE) -> Eliminatório (Must-have) | G55: Permite | I55: 5
A56: SIMULAÇÃO | B56: MULTIUNIDADE | C56: UNIDADES | D56: Permite adicionar mais de uma unidade na simulação, inclusive de empreendimentos diferentes | E56: 3 | F56: =VLOOKUP(E56,REGRAS!$A$2:$B$6,2,FALSE) -> Importante | H56: Esta funcionalidade não existe | I56: 0
A57: SIMULAÇÃO | B57: MULTIUNIDADE | C57: COMBO | D57: Permite utilizar combos na venda | E57: 3 | F57: =VLOOKUP(E57,REGRAS!$A$2:$B$6,2,FALSE) -> Importante | H57: Esta funcionalidade não existe | I57: 0
A58: SIMULAÇÃO | B58: MULTIUNIDADE | C58: AGLUTINADOR | D58: Permite utilizar unidades aglutinadas | E58: 3 | F58: =VLOOKUP(E58,REGRAS!$A$2:$B$6,2,FALSE) -> Importante | H58: Esta funcionalidade não existe | I58: 0
A59: SIMULAÇÃO | B59: PROPOSTA | C59: FLUXO DA PROPOSTA | D59: Permite, quando a tabela vinculada estiver vigente, avançar com o cenário escolhido para proposta. | E59: 5 | F59: =VLOOKUP(E59,REGRAS!$A$2:$B$6,2,FALSE) -> Eliminatório (Must-have) | H59: Não testa a tabela de pre~ço, mas pode avançar | I59: 4
A60: PROPOSTA | B60: RESERVA | C60: FLUXO DA RESERVA | D60: Permite seguir o fluxo da reserva quando na simulação | E60: 5 | F60: =VLOOKUP(E60,REGRAS!$A$2:$B$6,2,FALSE) -> Eliminatório (Must-have) | G60: Permite | H60: Não há onde observar todas as reservas | I60: 3
A61: PROPOSTA | B61: PV | C61: FLUXO DO PV | D61: Permite seguir o fluxo do pv quando na simulação | E61: 5 | F61: =VLOOKUP(E61,REGRAS!$A$2:$B$6,2,FALSE) -> Eliminatório (Must-have) | G61: Permite | I61: 5
A62: PROPOSTA | B62: CADASTRO | C62: QUALIFICAÇÃO DO PROSPECT | D62: Pemite adicionar o prospect ou vincular a uma oportunidade (já com os dados do prospect) | E62: 3 | F62: =VLOOKUP(E62,REGRAS!$A$2:$B$6,2,FALSE) -> Importante | H62: Esta funcionalidade não existe | I62: 0
A63: PROPOSTA | B63: CADASTRO | C63: VINCULO GERENTE>IMOBILIÁRIA>CORRETOR | D63: Permite vincular a uma estrutura de corretor/imobiliária/gerente | E63: 3 | F63: =VLOOKUP(E63,REGRAS!$A$2:$B$6,2,FALSE) -> Importante | H63: Esta funcionalidade não existe | I63: 0
A64: PROPOSTA | B64: MULTIUNIDADE | C64: UNIDADES | D64: Permite adicionar mais de uma unidade na simulação, inclusive de empreendimentos diferentes | E64: 3 | F64: =VLOOKUP(E64,REGRAS!$A$2:$B$6,2,FALSE) -> Importante | H64: Esta funcionalidade não existe | I64: 0
A65: PROPOSTA | B65: MULTIUNIDADE | C65: COMBO | D65: Permite utilizar combos na venda | E65: 3 | F65: =VLOOKUP(E65,REGRAS!$A$2:$B$6,2,FALSE) -> Importante | H65: Esta funcionalidade não existe | I65: 0
A66: PROPOSTA | B66: MULTIUNIDADE | C66: AGLUTINADOR | D66: Permite utilizar unidades aglutinadas | E66: 3 | F66: =VLOOKUP(E66,REGRAS!$A$2:$B$6,2,FALSE) -> Importante | H66: Esta funcionalidade não existe | I66: 0
A67: PROPOSTA | B67: ANÁLISE | C67: APROVAÇÃO>AUTOMÁTICA | D67: Quando o PV estiver dentro do valor definido a proposta é aprovada automaticamente | E67: 4 | F67: =VLOOKUP(E67,REGRAS!$A$2:$B$6,2,FALSE) -> Crítico para operação/adaptação | G67: Fornecedor informou que é possível mas não conseguiu demonstrar | I67: 4
A68: PROPOSTA | B68: ANÁLISE | C68: APROVAÇÃO>MULTINÍVEL | D68: Quando o PV estiver abaixo do valor definido ele, dependendo da variação, precisa passar por mais de uma pessoa para que a proposta seja aprovada | E68: 4 | F68: =VLOOKUP(E68,REGRAS!$A$2:$B$6,2,FALSE) -> Crítico para operação/adaptação | G68: Possui aprovação como parte do processo de geração do contrato. | H68: Só valida a proposta depois da análise de crédito e da visualização da documentação. | I68: 3
A69: PROPOSTA | B69: ANÁLISE | C69: REPROVAÇÃO | D69: Permite reprovar uma proposta informando seu motivo. | E69: 5 | F69: =VLOOKUP(E69,REGRAS!$A$2:$B$6,2,FALSE) -> Eliminatório (Must-have) | G69: Sim | H69: Porém não permite que a proposta seja adequada pelo corretor, sendo o Analista (Diretor) que precisa ratificar a proposta | I69: 1
A70: PROPOSTA | B70: ANÁLISE | C70: NOTIFICAÇÃO>MEIOS (EMAIL;WHATSAPP;SMS) | D70: Permite notificar todos os eventos da proposta por diversos meios eletrônicos | E70: 4 | F70: =VLOOKUP(E70,REGRAS!$A$2:$B$6,2,FALSE) -> Crítico para operação/adaptação | G70: Fornecedor informou que possuí | H70: Não conseguimos validar | I70: 1
A71: PROPOSTA | B71: ANÁLISE | C71: LINK PARA PORTAL | D71: Permite, na notificação, além da ação direta, quando possível, informar link para abertura da demanda no portal para ação. | E71: 2 | F71: =VLOOKUP(E71,REGRAS!$A$2:$B$6,2,FALSE) -> Desejável | H71: Esta funcionalidade não existe | I71: 0
A72: PROPOSTA | B72: CONTRATO | C72: FLUXO PARA CONTRATO | D72: Permite que a proposta aprovada evolua para o fluxo de contrato | E72: 5 | F72: =VLOOKUP(E72,REGRAS!$A$2:$B$6,2,FALSE) -> Eliminatório (Must-have) | G72: Sim | I72: 5
A73: PROPOSTA | B73: API INTEGRAÇÃO | C73: API INTEGRAÇÃO | D73: Permite que uma proposta seja cadastrada e aprovada/reprovada por API | E73: 3 | F73: =VLOOKUP(E73,REGRAS!$A$2:$B$6,2,FALSE) -> Importante | H73: Esta funcionalidade não existe | I73: 0
A74: CONTRATO | B74: DOCUMENTAÇÃO | C74: CONTROLE DE PENDÊNCIAS | D74: Controla os documentos a serem entregues a secretaria de vendas | E74: 4 | F74: =VLOOKUP(E74,REGRAS!$A$2:$B$6,2,FALSE) -> Crítico para operação/adaptação | G74: Sim | I74: 5
A75: CONTRATO | B75: DOCUMENTAÇÃO | C75: LISTA DE DOCUMENTOS>PADRÃO E EXTRAS | D75: Permite definir uma lista de documentos obrigatórios e desejáveis para a venda | E75: 2 | F75: =VLOOKUP(E75,REGRAS!$A$2:$B$6,2,FALSE) -> Desejável | G75: Apenas os obrigatórios e são fixos, não podem ser escolhidos. | I75: 3
A76: CONTRATO | B76: DOCUMENTAÇÃO | C76: CONTROLE DE RECEPÇÃO | D76: Controla a data da recepção dos documentos | E76: 3 | F76: =VLOOKUP(E76,REGRAS!$A$2:$B$6,2,FALSE) -> Importante | G76: Sim, por log | I76: 4
A77: CONTRATO | B77: DOCUMENTAÇÃO | C77: CONTROLE DE PRAZO | D77: Controla o prazo para entrega e análise dos documentos | E77: 3 | F77: =VLOOKUP(E77,REGRAS!$A$2:$B$6,2,FALSE) -> Importante | H77: Esta funcionalidade não existe | I77: 0
A78: CONTRATO | B78: DOCUMENTAÇÃO | C78: APROVAÇÃO | D78: Permite obrigatoriedade na aprovação dos documentos | E78: 4 | F78: =VLOOKUP(E78,REGRAS!$A$2:$B$6,2,FALSE) -> Crítico para operação/adaptação | G78: Sim | H78: Não há aviso ou cobrança de SLA | I78: 4
A79: CONTRATO | B79: CRÉDITO | C79: LISTA DE DOCUMENTOS>PADRÃO E EXTRAS | D79: Permite definir uma lista de documentos obrigatórios e desejáveis para a venda | E79: 3 | F79: =VLOOKUP(E79,REGRAS!$A$2:$B$6,2,FALSE) -> Importante | H79: Esta funcionalidade não existe | I79: 0
A80: CONTRATO | B80: CRÉDITO | C80: CONTROLE DE PENDÊNCIAS | D80: Controla os documentos a serem entregues a secretaria de vendas | E80: 2 | F80: =VLOOKUP(E80,REGRAS!$A$2:$B$6,2,FALSE) -> Desejável | H80: Esta funcionalidade não existe | I80: 0
A81: CONTRATO | B81: CRÉDITO | C81: APROVAÇÃO | D81: Permite obrigatoriedade na aprovação do crédito | E81: 2 | F81: =VLOOKUP(E81,REGRAS!$A$2:$B$6,2,FALSE) -> Desejável | G81: Sim | H81: Não há aviso ou cobrança de SLA | I81: 4
A82: CONTRATO | B82: CONTROLE DE RECEPÇÃO | C82: INTEGRAÇÃO COM SISTEMAS DE CRÉDITO | D82: Possibilita a consulta de crédito (score e outros dados) em sistemas terceiros de análise de crédito | E82: 2 | F82: =VLOOKUP(E82,REGRAS!$A$2:$B$6,2,FALSE) -> Desejável | H82: Esta funcionalidade não existe | I82: 0
A83: CONTRATO | B83: CONTRATO | C83: MODELOS DE CONTRATO>TAGS | D83: Possui local para gravação dos modelos dos contratos e sua veinculação as TAGS do sistema | E83: 5 | F83: =VLOOKUP(E83,REGRAS!$A$2:$B$6,2,FALSE) -> Eliminatório (Must-have) | G83: Sim | I83: 5
A84: CONTRATO | B84: CONTRATO | C84: CLAUSULAS AVULSAS>K | D84: Permite adicionar clausulas avulsas ao contrato, tanto pré-cadastradas (lista com TAGS) quanto de digitação livre | E84: 4 | F84: =VLOOKUP(E84,REGRAS!$A$2:$B$6,2,FALSE) -> Crítico para operação/adaptação | G84: Sim | I84: 5
A85: CONTRATO | B85: CONTRATO | C85: EXPORTAÇÃO DOC E PDF | D85: Pode exportar o contrato assinado em PDF e não assinado em DOC/PDF | E85: 4 | F85: =VLOOKUP(E85,REGRAS!$A$2:$B$6,2,FALSE) -> Crítico para operação/adaptação | G85: Sim | I85: 5
A86: CONTRATO | B86: ASSINATURA | C86: INTEGRAÇÃO COM ASSINATURA DIGITAL | D86: É possível enviar automaticamente o contrato para plataformas de assinatura digital | E86: 3 | F86: =VLOOKUP(E86,REGRAS!$A$2:$B$6,2,FALSE) -> Importante | G86: Sim | I86: 5
A87: CONTRATO | B87: ASSINATURA | C87: ACOMPANHAMENTO DA ASSINATURA | D87: Quando há integração com sistema de assinatura digital é possível verificar, no sistema, para quem foi enviado e quem já assinou. | E87: 3 | F87: =VLOOKUP(E87,REGRAS!$A$2:$B$6,2,FALSE) -> Importante | H87: Esta funcionalidade não existe | I87: 0
A88: CONTRATO | B88: ASSINATURA | C88: VENCIMENTO>CONTROLE PRAZO | D88: Com ou sem integração, deve ser possível controlar o tempo no processo de assinatura. | E88: 3 | F88: =VLOOKUP(E88,REGRAS!$A$2:$B$6,2,FALSE) -> Importante | H88: Esta funcionalidade não existe | I88: 0
A89: CONTRATO | B89: ASSINATURA | C89: VENCIMENTO>EXTENSÃO DE PRAZO | D89: Com ou sem integração, deve ser possível extender o prazo de assinatura | E89: 3 | F89: =VLOOKUP(E89,REGRAS!$A$2:$B$6,2,FALSE) -> Importante | H89: Esta funcionalidade não existe | I89: 0
A90: CONTRATO | B90: ASSINATURA | C90: VENCIMENTO>CANCELAMENTO | D90: Automatico ou Manual deve ser possível cancelar um contrato por falta de assinatura | E90: 4 | F90: =VLOOKUP(E90,REGRAS!$A$2:$B$6,2,FALSE) -> Crítico para operação/adaptação | G90: Sim, manualmente apenas | I90: 4
A91: CONTRATO | B91: ERP | C91: INTEGRAÇÃO DA VENDA | D91: Quando o contrato é assinado é necessário registrar a venda no sistma ERP atraves de integração, preferencialmente, nativa. | E91: 4 | F91: =VLOOKUP(E91,REGRAS!$A$2:$B$6,2,FALSE) -> Crítico para operação/adaptação | G91: Sim, com ressalvas | H91: Não conseguimos validar a venda com financiamento próprio e 2 taxas de correção | I91: 4
A92: CONTRATO | B92: ERP | C92: INTEGRAÇÃO DE DISTRATO | D92: Quando o contrato é cancelado é necessário registrar a venda no sistma ERP atraves de integração, preferencialmente, nativa. O fluxo inverso deve ser possível, do ERP informando o CRM | E92: 4 | F92: =VLOOKUP(E92,REGRAS!$A$2:$B$6,2,FALSE) -> Crítico para operação/adaptação | H92: Não há integração, deve ser feita manualmente em ambos os sistemas | I92: 0
A93: CONTRATO | B93: COMISSÃO | C93: PADRÃO | D93: Deve controlar o pagamento de comissão de acordo com o definido junto a imobiliária, sendo possível edição manual | E93: 4 | F93: =VLOOKUP(E93,REGRAS!$A$2:$B$6,2,FALSE) -> Crítico para operação/adaptação | G93: Sim | I93: 5
A94: CONTRATO | B94: COMISSÃO | C94: POR DENTRO DO CONTRATO | D94: Deve permitir que a comissão seja embutida no contrato de venda como parte do valor da imobiliária para repasse | E94: 3 | F94: =VLOOKUP(E94,REGRAS!$A$2:$B$6,2,FALSE) -> Importante | G94: Sim | I94: 5
A95: CONTRATO | B95: NOTIFICAÇÕES | C95: MEIOS (EMAIL, SMS, WHATSAPP) | D95: Todos os eventos do contrato devem emitir notificação por meio eletrônico | E95: 3 | F95: =VLOOKUP(E95,REGRAS!$A$2:$B$6,2,FALSE) -> Importante | G95: Fornecedor informa que sim, mas não conseguimos simular | I95: 1
A96: CONTRATO | B96: NOTIFICAÇÕES | C96: LINK PORTAL | D96: Na notificação deve constar link que permita direcionamento direto para a ação ou informação vinculada | E96: 2 | F96: =VLOOKUP(E96,REGRAS!$A$2:$B$6,2,FALSE) -> Desejável | H96: Esta funcionalidade não existe | I96: 0

Sheet RESULTADO HYPNOBOX
D2: MÉDIA DAS NOTAS
B3: 5 | D3: =AVERAGEIF(HYPNOBOX!E:E,B3,HYPNOBOX!I:I) -> 3.7647059
B4: 4 | D4: =AVERAGEIF(HYPNOBOX!E:E,B4,HYPNOBOX!I:I) -> 2.7
B5: 3 | D5: =AVERAGEIF(HYPNOBOX!E:E,B5,HYPNOBOX!I:I) -> 0.73529412 | E5: =COUNTIF(HYPNOBOX!E:E,3) -> 34 | F5: =D5*E5 -> 25
B6: 2 | D6: =AVERAGEIF(HYPNOBOX!E:E,B6,HYPNOBOX!I:I) -> 1.1538462 | E6: =COUNTIF(HYPNOBOX!E:E,2) -> 13 | F6: =D6*E6 -> 15
B7: 1 | D7: =AVERAGEIF(HYPNOBOX!E:E,B7,HYPNOBOX!I:I) -> 0.4 | E7: =COUNTIF(HYPNOBOX!E:E,1) -> 5 | F7: =D7*E7 -> 2
B8: Unificada 3, 2 e 1 | D8: =F8/E8 -> 0.80769231 | E8: =SUM(E5:E7) -> 52 | F8: =SUM(F5:F7) -> 42
B10: ELIMINIAÇÃO | E10: nota de corte
B11: 5 | D11: =IF(COUNTIFS(HYPNOBOX!E:E,5,HYPNOBOX!I:I,"<"&E11)>0,"ELIMINADO","OK") -> ELIMINADO | E11: 4
B12: 4 | D12: =IF(COUNTIFS(HYPNOBOX!E:E,5,HYPNOBOX!I:I,"<"&E12)>0,"ELIMINADO","OK") -> ELIMINADO | E12: 3
B14: Nota Final
B15: 5 | C15: 0.6 | D15: =D3 -> 3.7647059 | E15: =C15*D15 -> 2.2588235
B16: 4 | C16: 0.3 | D16: =D4 -> 2.7 | E16: =C16*D16 -> 0.81
B17: 1,2,3 | C17: 0.1 | D17: =D8 -> 0.80769231 | E17: =C17*D17 -> 0.080769231
B19: NOTA FINAL | E19: =IF(OR(D11="ELIMINADO",D12="ELIMINADO"),0,SUM(E15:E17)) -> 0

Sheet REGRAS
A1: peso | B1: Avalia o quanto o requisito é importante para o negócio da City
A2: 5 | B2: Eliminatório (Must-have) | C2: Se não tiver de forma nativa ou comprovadamente atendida (configuração/módulo oficial), descarta o fornecedor. Sem isso, o sistema não atende o objetivo, compliance/segurança, ou o processo principal.
A3: 4 | B3: Crítico para operação/adaptação | C3: Se faltar, o risco de implantação e adoção sobe muito: muda processo demais, cria gargalo, aumenta erro, compromete controles. Só aceitável se o fornecedor resolver com configuração robusta, módulo oficial ou integração sólida (sem “promessa”).
A4: 3 | B4: Importante | C4: Entra forte na comparação entre fornecedores. Se faltar, gera custo/complexidade (customização, integrações, retrabalho) que precisa ser considerado no TCO, mas ainda pode ser viável comprar.
A5: 2 | B5: Desejável | C5: Traz ganho claro, mas não é decisivo. Se faltar, dá para conviver com ajuste de processo ou complemento leve.
A6: 1 | B6: Baixo valor na compra (Nice-to-have) | C6: Ajuda, mas não influencia a decisão. Pode ficar para “melhoria futura” ou solução paralela sem impacto.
A8: O que avaliar | B8: O que ter em mente no momento de dar a nota ao fornecedor quanto a um determinado requisito
A9: A | B9: Impacto no processo core (para o dia a dia rodar)
A10: B | B10: Risco (compliance, auditoria, segurança, fraude, LGPD, rastreabilidade)
A11: C | B11: Custo/complexidade de contorno (customização, integrações, operação manual)
A12: D | B12: Adoção (usuários conseguem trabalhar ou vão rejeitar)
A14: Notas | B14: Informa o quanto o fornecedor, olhando pelo prisma do que avaliar, atender o processo
A15: 5 | B15: Atende completamente
A16: 4 | B16: Atende quase tudo (lacunas pontuais) | C16: Atende o fluxo principal e a maioria dos cenários. Restam lacunas pontuais que não comprometem a operação, mas precisam ser tratadas (exceções específicas, detalhes de relatório/controle).
A17: 3 | B17: Atende parcialmente (operável com lacunas relevantes) | C17: O processo roda em parte, mas existem lacunas que exigem ajustes operacionais relevantes (exceções não cobertas, controles faltando, etapas críticas ausentes).
A18: 2 | B18: Atende muito pouco | C18: Cobre só partes isoladas, não sustenta o fluxo ponta a ponta do requisito. Falha em cenários comuns.
A19: 1 | B19: Não atende | C19: Não executa o processo necessário para aquele requisito (não passa no cenário mínimo).
C20: Cobre o requisito ponta a ponta, incluindo cenários principais e exceções relevantes, com os controles/saídas esperadas.
A22: Regras | B22: Racional | C22: Resultado
B23: Peso 5 com nota inferior a 3 (0 a 4) | C23: Desclassificado
B24: Peso 4 com nota inferior a 3 (0 a 4) | C24: Zera a nota
B25: Peso 3, 2 e 1 | C25: Mantém a nota
A27: Nota Final | C27: Nota classificação final
B28: 0,6 x Média(Nota5) + 0,3xMédia(Nota4) + 0,1*Média(Notas3,2,1)

Sheet REQUISITOS - BASE
A1: ÁREA: | B1: COMERCIAL
A2: PATROCINADOR | B2: MICHEL
A3: AN-TI | B3: DANIEL
A4: DATA
A5: CITY | G5: porque a sua nota foi esta?
A7: ÁREA | B7: PROCESSO | C7: REQUISITO | D7: Descrição | E7: PESO | F7: DESCRIÇÃO PESO | G7: POSITIVO | H7: NEGATIVO | I7: NOTA
A8: GERAL | B8: EMPREENDIMENTO | C8: CADASTRO | D8: Realizar o cadastro dos dados relacionados ao empreendimento, como data de lançamento, número da RI, data de entrega, área, nome fantasia e razão social da empresa, endereço, posição geográfica, conta de pagamento, código do empreendimento no erp, amenidades, pontos fortes e afins. | E8: 5 | F8: =VLOOKUP(E8,REGRAS!$A$2:$B$6,2,FALSE) -> Eliminatório (Must-have)
A9: GERAL | B9: EMPREENDIMENTO | C9: MATERIAL DE APOIO A VENDA | D9: Permite anexar ao empreendimento material que auxilie o processo de venda, como vídeos, imagens e scripts de venda, quebra de resistencia e afins. | E9: 1 | F9: =VLOOKUP(E9,REGRAS!$A$2:$B$6,2,FALSE) -> Baixo valor na compra (Nice-to-have)
A10: GERAL | B10: EMPREENDIMENTO | C10: UHs/LOTE | D10: Cadastro das unidades/lotes com suas características (m2, andar, local e etc) | E10: 5 | F10: =VLOOKUP(E10,REGRAS!$A$2:$B$6,2,FALSE) -> Eliminatório (Must-have)
A11: GERAL | B11: EMPREENDIMENTO | C11: UHs/LOTE>TAGS | D11: Opção de marcar unidades, como, promoção, decorada, cobertura ou outra tag desejada | E11: 2 | F11: =VLOOKUP(E11,REGRAS!$A$2:$B$6,2,FALSE) -> Desejável
A12: GERAL | B12: EMPREENDIMENTO | C12: UHs/LOTE>AGLUTINADOR | D12: Permite unificar unidades avulsas em uma única unidade para a venda, incluso valor próprio | E12: 3 | F12: =VLOOKUP(E12,REGRAS!$A$2:$B$6,2,FALSE) -> Importante
A13: GERAL | B13: EMPREENDIMENTO | C13: UHs/LOTE>COMBO | D13: Permite aglutinar unidades apenas como sugestão de venda com valor próprio (desconto por volume) | E13: 3 | F13: =VLOOKUP(E13,REGRAS!$A$2:$B$6,2,FALSE) -> Importante
A14: GERAL | B14: EMPREENDIMENTO | C14: TABELA DE PREÇO>CADASTRO | D14: Cadastrar tabelas de preço para as unidades | E14: 5 | F14: =VLOOKUP(E14,REGRAS!$A$2:$B$6,2,FALSE) -> Eliminatório (Must-have)
A15: GERAL | B15: EMPREENDIMENTO | C15: TABELA DE PREÇO>ATUALIZAÇÃO MONETÁRIA | D15: Permite informar atualização monetária para atualização das tabelas de preço, inclusive, com regra de arredondamento e calendário de execução. | E15: 5 | F15: =VLOOKUP(E15,REGRAS!$A$2:$B$6,2,FALSE) -> Eliminatório (Must-have)
A16: GERAL | B16: EMPREENDIMENTO | C16: TABELA DE PREÇO>EVOLUÇÃO DO PREÇO | D16: Permite verificar, para uma unidade, a evolução de preço ao longo do tempo | E16: 2 | F16: =VLOOKUP(E16,REGRAS!$A$2:$B$6,2,FALSE) -> Desejável
A17: GERAL | B17: EMPREENDIMENTO | C17: TABELA DE PREÇO>EXCEÇÕES > AGLUTINADOR | D17: Permite cadastrar preço para unidades aglutinadas. | E17: 3 | F17: =VLOOKUP(E17,REGRAS!$A$2:$B$6,2,FALSE) -> Importante
A18: GERAL | B18: EMPREENDIMENTO | C18: TABELA DE PREÇO>EXCEÇÕES > COMBO | D18: Permite cadastrar preço para unidades agrupadas no combo. | E18: 3 | F18: =VLOOKUP(E18,REGRAS!$A$2:$B$6,2,FALSE) -> Importante
A19: GERAL | B19: EMPREENDIMENTO | C19: API INTEGRAÇÃO | D19: Integração das rotinas do empreendimento (cadastro, material de apoio a vendas, uhs, tabela de preço) via API | E19: 4 | F19: =VLOOKUP(E19,REGRAS!$A$2:$B$6,2,FALSE) -> Crítico para operação/adaptação
... A94: CONTRATO | B94: NOTIFICAÇÕES | C94: LINK PORTAL | D94: Na notificação deve constar link que permita direcionamento direto para a ação ou informação vinculada | E94: 2 | F94: =VLOOKUP(E94,REGRAS!$A$2:$B$6,2,FALSE) -> Desejável
